app/__init__.py
app/cli.py
app/config.py
app/database.py
app/main.py
app/models.py
app/mymcp.py
app/orm.py
app/schemas.py
mcp_chatbot-0.1.0.dist-info/METADATA
mcp_chatbot-0.1.0.dist-info/WHEEL
mcp_chatbot-0.1.0.dist-info/entry_points.txt
mcp_chatbot-0.1.0.dist-info/top_level.txt
mcp_chatbot-0.1.0.dist-info/RECORD
