Metadata-Version: 2.4
Name: mcp-chatbot
Version: 0.1.0
Summary: Add your description here
Requires-Python: >=3.13
Requires-Dist: fastapi>=0.118.0
Requires-Dist: httpx>=0.28.1
Requires-Dist: mcp[cli]>=1.16.0
Requires-Dist: pydantic-settings>=2.11.0
Requires-Dist: sqlalchemy>=2.0.43
Requires-Dist: uvicorn>=0.37.0
